Metadata-Version: 2.1
Name: opal-client-fork
Version: 0.1.25
Summary: OPAL is an administration layer for Open Policy Agent (OPA), detecting changes to both policy and data and pushing live updates to your agents. The opal-client is deployed alongside a policy-store (e.g: OPA), keeping it up-to-date, by connecting to an opal-server and subscribing to pub/sub updates for policy and policy data changes.
Home-page: https://github.com/authorizon/opal
Author: Or Weis, Asaf Cohen
Author-email: or@authorizon.com
License: Apache 2.0
Platform: UNKNOWN
Classifier: Operating System :: OS Independent
Classifier: License :: OSI Approved :: Apache Software License
Classifier: Programming Language :: Python
Classifier: Programming Language :: Python :: 3
Classifier: Programming Language :: Python :: 3.7
Classifier: Programming Language :: Python :: 3.8
Classifier: Programming Language :: Python :: 3.9
Classifier: Topic :: Internet :: WWW/HTTP :: HTTP Servers
Classifier: Topic :: Internet :: WWW/HTTP :: WSGI
Requires-Python: >=3.7
Requires-Dist: GitPython
Requires-Dist: aiofiles
Requires-Dist: aiohttp
Requires-Dist: broadcaster[postgres]
Requires-Dist: colorama
Requires-Dist: fastapi (==0.65.2)
Requires-Dist: fastapi-websocket-pubsub (>=0.1.18)
Requires-Dist: fastapi-websocket-rpc (>=0.1.18)
Requires-Dist: gunicorn
Requires-Dist: idna (<3,>=2.5)
Requires-Dist: ipython
Requires-Dist: loguru (==0.5.3)
Requires-Dist: opal-common-fork (==0.1.25)
Requires-Dist: psutil (==5.8.0)
Requires-Dist: pydantic[email]
Requires-Dist: pyjwt[crypto]
Requires-Dist: python-decouple
Requires-Dist: tenacity (==6.3.1)
Requires-Dist: typer
Requires-Dist: typing-extensions
Requires-Dist: uvicorn[standard]
Requires-Dist: websockets
